docdb/__init__.py
docdb/collection.py
docdb/exceptions.py
docdb-0.0.7.dist-info/WHEEL
docdb-0.0.7.dist-info/METADATA
docdb-0.0.7.dist-info/RECORD
