Metadata-Version: 2.1
Name: docdb
Version: 0.0.7
Summary: A lightweight, performant, document database built on SQLite for Python3
Author: Dan Sikes
Author-email: dansikes7@gmail.com
Requires-Python: >=3.9,<4.0
Classifier: Programming Language :: Python :: 3
Classifier: Programming Language :: Python :: 3.10
Classifier: Programming Language :: Python :: 3.9
Requires-Dist: msgpack (>=1.0.3,<2.0.0)
Requires-Dist: pytest-cov (>=3.0.0,<4.0.0)
